LICENSE
README.md
micli.py
setup.py
miservice/__init__.py
miservice/miaccount.py
miservice/miiocommand.py
miservice/miioservice.py
miservice/minaservice.py
miservice.egg-info/PKG-INFO
miservice.egg-info/SOURCES.txt
miservice.egg-info/dependency_links.txt
miservice.egg-info/requires.txt
miservice.egg-info/top_level.txt