Metadata-Version: 2.1
Name: miservice
Version: 2.2.0
Summary: XiaoMi Cloud Service
Home-page: https://github.com/Yonsm/MiService
Author: Yonsm
Author-email: Yonsm@qq.com
License: MIT
Classifier: Programming Language :: Python :: 3
Classifier: License :: OSI Approved :: MIT License
Classifier: Operating System :: OS Independent
Requires-Python: >=3.7
License-File: LICENSE
Requires-Dist: aiohttp
